fasoarzeka/__init__.py
fasoarzeka/base.py
fasoarzeka/constants.py
fasoarzeka/exceptions.py
fasoarzeka/main.py
fasoarzeka/utils.py
fasoarzeka-0.1.2.dist-info/licenses/LICENSE
fasoarzeka-0.1.2.dist-info/METADATA
fasoarzeka-0.1.2.dist-info/WHEEL
fasoarzeka-0.1.2.dist-info/top_level.txt
fasoarzeka-0.1.2.dist-info/RECORD
