Metadata-Version: 2.4
Name: fasoarzeka
Version: 0.1.2
Summary: API non officielle de paiement mobile pour le service FASO ARZEKA au Burkina Faso
Author-email: Mohamed ZEBA <m.zeba@mzeba.dev>
License-Expression: MIT
Project-URL: Homepage, https://pypi.org/project/fasoarzeka/
Project-URL: Issues, https://github.com/mzeba/fasoarzeka/issues
Project-URL: Repository, https://github.com/mzeba/fasoarzeka.git
Keywords: fasoarzeka ,burkina payment api,mobile money,payment api,burkina faso
Classifier: Development Status :: 3 - Alpha
Classifier: Programming Language :: Python :: 3
Classifier: Operating System :: OS Independent
Requires-Python: >=3.8
License-File: LICENSE
Requires-Dist: requests>=2.31.0
Requires-Dist: urllib3<1.27
Provides-Extra: dev
Requires-Dist: pytest; extra == "dev"
Dynamic: license-file
